openweather_api/__init__.py
openweather_api/client.py
openweather_api/core.py
openweather_api/settings.py
openweather_api/utils.py
openweather_api-0.1.0.dist-info/LICENSE
openweather_api-0.1.0.dist-info/WHEEL
openweather_api-0.1.0.dist-info/METADATA
openweather_api-0.1.0.dist-info/RECORD
